unsplash_search/__init__.py
unsplash_search/unsplash.py
unsplash_search-0.2.0.dist-info/LICENSE.txt
unsplash_search-0.2.0.dist-info/METADATA
unsplash_search-0.2.0.dist-info/WHEEL
unsplash_search-0.2.0.dist-info/top_level.txt
unsplash_search-0.2.0.dist-info/RECORD
