Metadata-Version: 2.1
Name: unsplash-search
Version: 0.2.0
Summary: Search unsplash for photos
Home-page: https://github.com/orlandodiaz/unsplash_search
Author: Orlando Diaz
Author-email: orlandodiaz.dev@gmail.com
License: UNKNOWN
Platform: UNKNOWN
Classifier: Programming Language :: Python :: 3
Classifier: License :: OSI Approved :: MIT License
Classifier: Operating System :: OS Independent
Requires-Dist: requests (>=2.19.1)
Requires-Dist: log3 (>=0.1.6)
